setup.py
gtchecker/_init_.py
gtchecker/client.py
gtchecker/errors.py
gtchecker.com.egg-info/PKG-INFO
gtchecker.com.egg-info/SOURCES.txt
gtchecker.com.egg-info/dependency_links.txt
gtchecker.com.egg-info/top_level.txt